milea_base/__init__.py
milea_base/admin.py
milea_base/apps.py
milea_base/fields.py
milea_base/models.py
milea_base/settings.py
milea_base/urls.py
milea_base/utils.py
milea_base/locale/de/LC_MESSAGES/django.mo
milea_base/locale/de/LC_MESSAGES/django.po
milea_base/migrations/__init__.py
milea_base/migrations/__pycache__/__init__.cpython-312.pyc
milea_base/static/admin/img/icon-calendar.svg
milea_base/static/admin/img/icon-clock.svg
milea_base/static/admin/js/SelectFilter2.js
milea_base/static/admin/js/change_form.js
milea_base/static/admin/js/admin/RelatedObjectLookups.js
milea_base/static/milea_base/css/custom.css
milea_base/static/milea_base/css/form.css
milea_base/static/milea_base/css/select2.css
milea_base/static/milea_base/css/tabler-icons.css
milea_base/static/milea_base/css/tabler-vendor.css
milea_base/static/milea_base/css/tabler.css
milea_base/static/milea_base/css/fonts/tabler-icons.eot
milea_base/static/milea_base/css/fonts/tabler-icons.ttf
milea_base/static/milea_base/css/fonts/tabler-icons.woff
milea_base/static/milea_base/css/fonts/tabler-icons.woff2
milea_base/static/milea_base/img/favicon.ico
milea_base/static/milea_base/img/file-icon.jpg
milea_base/static/milea_base/img/logo.png
milea_base/static/milea_base/img/no-img.jpg
milea_base/static/milea_base/img/user-icon.png
milea_base/static/milea_base/img/illustrations/login.svg
milea_base/static/milea_base/js/custom.js
milea_base/static/milea_base/js/form.js
milea_base/static/milea_base/js/preloader.js
milea_base/static/milea_base/js/tabler.js
milea_base/static/milea_base/js/tom-select.complete.min.js
milea_base/templates/admin/actions.html
milea_base/templates/admin/app_index.html
milea_base/templates/admin/app_list.html
milea_base/templates/admin/app_menu_list.html
milea_base/templates/admin/base.html
milea_base/templates/admin/base_auth.html
milea_base/templates/admin/base_site.html
milea_base/templates/admin/change_form.html
milea_base/templates/admin/change_form_object_tools.html
milea_base-0.5.2.dist-info/METADATA
milea_base-0.5.2.dist-info/WHEEL
milea_base-0.5.2.dist-info/top_level.txt
milea_base-0.5.2.dist-info/RECORD
