Metadata-Version: 2.1
Name: milea-base
Version: 0.5.2
Summary: Milea Framework - Milea Base Module
Author: red-pepper-services
Author-email: pypi@schiegg.at
License: MIT
Requires-Dist: django-celery-results >=2.5.1
Requires-Dist: django-celery-beat >=2.5.0
Requires-Dist: django-countries >=7.5.1
Requires-Dist: django-currentuser >=0.7.0
Requires-Dist: django-environ >=0.11.2
Requires-Dist: django-object-actions >=4.2.0
Requires-Dist: django >=5.0.2
Requires-Dist: djangorestframework >=3.14.0
Requires-Dist: pillow >=10.2.0
Requires-Dist: pymysql >=1.1.0
Requires-Dist: requests >=2.31.0
Requires-Dist: milea-users >=0.2
Requires-Dist: milea-notify >=0.2
Requires-Dist: milea-licence >=0.1
